{
    "@class": "Animation",
    "id": {
        "uuid": "645D9390-5770-4273-BCA1-0598A1BE5268"
    },
    "tracks": [
        {
            "@class": "Vector3BehaviorTrack",
            "clips": [
                {
                    "@class": "Vector3BehaviorClip",
                    "beginTime": 0,
                    "duration": 1033,
                    "script": "Vector3ValueBehaviorClipScript",
                    "behavior": {
                        "@class": "Vector3PlainBehavior",
                        "times": [
                            0,
                            33,
                            99,
                            166,
                            199,
                            233,
                            266,
                            299,
                            333,
                            499,
                            633,
                            666,
                            699,
                            766,
                            799,
                            899,
                            933,
                            1033
                        ],
                        "values": [
                            0.0,
                            0.4564000070095062,
                            0.0,
                            0.0,
                            0.4564000070095062,
                            0.0,
                            0.0,
                            0.4564000070095062,
                            0.0,
                            0.0,
                            0.4564000070095062,
                            0.0,
                            0.0,
                            0.4564000070095062,
                            0.0,
                            0.0,
                            0.4564000070095062,
                            0.0,
                            0.0,
                            0.4564000070095062,
                            0.0,
                            0.0,
                            0.4564000070095062,
                            0.0,
                            0.0,
                            0.4564000070095062,
                            0.0,
                            0.0,
                            0.4564000070095062,
                            0.0,
                            0.0,
                            0.4564000070095062,
                            0.0,
                            0.0,
                            0.4564000070095062,
                            0.0,
                            0.0,
                            0.4564000070095062,
                            0.0,
                            0.0,
                            0.4564000070095062,
                            0.0,
                            0.0,
                            0.4564000070095062,
                            0.0,
                            0.0,
                            0.4564000070095062,
                            0.0,
                            0.0,
                            0.4564000070095062,
                            0.0,
                            0.0,
                            0.4564000070095062,
                            0.0
                        ]
                    }
                }
            ],
            "script": "Vector3BehaviorTrackScript",
            "accessor": "PositionBlendAccessor"
        },
        {
            "@class": "QuaternionBehaviorTrack",
            "clips": [
                {
                    "@class": "QuaternionBehaviorClip",
                    "beginTime": 0,
                    "duration": 1033,
                    "script": "QuaternionValueBehaviorClipScript",
                    "behavior": {
                        "@class": "QuaternionPlainBehavior",
                        "times": [
                            0,
                            33,
                            99,
                            166,
                            199,
                            233,
                            266,
                            299,
                            333,
                            499,
                            633,
                            666,
                            699,
                            766,
                            799,
                            899,
                            933,
                            1033
                        ],
                        "values": [
                            0.5937029719352722,
                            0.1328846961259842,
                            0.12818077206611634,
                            0.7832165360450745,
                            0.5818758606910706,
                            0.13586047291755677,
                            0.13125716149806977,
                            0.7910335063934326,
                            0.5508413910865784,
                            0.14301550388336183,
                            0.13451191782951356,
                            0.8111885786056519,
                            0.5808054208755493,
                            0.1273064911365509,
                            0.09669748693704605,
                            0.7981902956962586,
                            0.6168441772460938,
                            0.11121078580617905,
                            0.06719794124364853,
                            0.7762859463691711,
                            0.6405629515647888,
                            0.09588641673326493,
                            0.039009928703308108,
                            0.7608962655067444,
                            0.645868718624115,
                            0.08451377600431442,
                            0.014947591349482537,
                            0.7586089968681336,
                            0.6373196840286255,
                            0.07751946896314621,
                            -0.00257308641448617,
                            0.766686201095581,
                            0.6213113069534302,
                            0.07472364604473114,
                            -0.011158452369272709,
                            0.7799128890037537,
                            0.5591499209403992,
                            0.08625239878892899,
                            0.0057965237647295,
                            0.8245473504066467,
                            0.5558497309684753,
                            0.07854767143726349,
                            -0.017446504905819894,
                            0.827379584312439,
                            0.5554322600364685,
                            0.0779603123664856,
                            -0.02016310580074787,
                            0.827653706073761,
                            0.5573153495788574,
                            0.07778127491474152,
                            -0.021296417340636255,
                            0.8263753056526184,
                            0.568581759929657,
                            0.0799427181482315,
                            -0.015339180827140808,
                            0.818589448928833,
                            0.5768051743507385,
                            0.08325684070587158,
                            -0.005660082679241896,
                            0.8126081824302673,
                            0.5984998941421509,
                            0.10218141973018646,
                            0.04700816795229912,
                            0.7931879162788391,
                            0.6019347906112671,
                            0.1098870113492012,
                            0.06820575147867203,
                            0.7880021333694458,
                            0.5955449938774109,
                            0.13267813622951508,
                            0.12784183025360108,
                            0.7819073796272278
                        ]
                    }
                }
            ],
            "script": "QuaternionBehaviorTrackScript",
            "accessor": "RotationQBlendAccessor"
        },
        {
            "@class": "Vector3BehaviorTrack",
            "clips": [
                {
                    "@class": "Vector3BehaviorClip",
                    "beginTime": 0,
                    "duration": 1033,
                    "script": "Vector3ValueBehaviorClipScript",
                    "behavior": {
                        "@class": "Vector3PlainBehavior",
                        "times": [
                            0,
                            33,
                            99,
                            166,
                            199,
                            233,
                            266,
                            299,
                            333,
                            499,
                            633,
                            666,
                            699,
                            766,
                            799,
                            899,
                            933,
                            1033
                        ],
                        "values": [
                            1.0,
                            0.9998999238014221,
                            1.0,
                            0.9999999403953552,
                            0.9998999834060669,
                            1.0,
                            1.0,
                            0.9998999238014221,
                            1.0,
                            1.0,
                            0.9998999834060669,
                            1.0,
                            1.0,
                            0.9998999834060669,
                            1.0,
                            0.9999999403953552,
                            0.9998999834060669,
                            1.0,
                            1.0,
                            0.9998999834060669,
                            1.0,
                            1.0,
                            0.9998999834060669,
                            1.0,
                            1.0,
                            0.9998999834060669,
                            0.9999999403953552,
                            1.0,
                            0.9998999834060669,
                            0.9999999403953552,
                            1.0,
                            0.9999000430107117,
                            1.0,
                            1.0,
                            0.9998999834060669,
                            0.9999999403953552,
                            1.0,
                            0.9998999834060669,
                            1.0,
                            0.9999999403953552,
                            0.9998999834060669,
                            1.0,
                            1.0,
                            0.9998999834060669,
                            0.9999999403953552,
                            0.9999999403953552,
                            0.9998999834060669,
                            1.0,
                            1.0,
                            0.9998999834060669,
                            1.0,
                            1.0,
                            0.9998999238014221,
                            1.0
                        ]
                    }
                }
            ],
            "script": "Vector3BehaviorTrackScript",
            "accessor": "ScaleBlendAccessor"
        }
    ]
}