{
    "@class": "Animation",
    "id": {
        "uuid": "868C3573-2746-4A4B-9322-02A95CDA9030"
    },
    "tracks": [
        {
            "@class": "Vector3BehaviorTrack",
            "clips": [
                {
                    "@class": "Vector3BehaviorClip",
                    "beginTime": 0,
                    "duration": 833,
                    "script": "Vector3ValueBehaviorClipScript",
                    "behavior": {
                        "@class": "Vector3PlainBehavior",
                        "times": [
                            0,
                            166,
                            199,
                            233,
                            266,
                            299,
                            333,
                            366,
                            399,
                            433,
                            466,
                            499,
                            533,
                            566,
                            599,
                            633,
                            666,
                            699,
                            733,
                            766,
                            799,
                            833
                        ],
                        "values": [
                            -0.04139995202422142,
                            0.10399986803531647,
                            0.002300061285495758,
                            -0.041399966925382617,
                            0.10399989038705826,
                            0.0023000433575361969,
                            -0.04139997065067291,
                            0.10399989783763886,
                            0.002300039865076542,
                            -0.04139997437596321,
                            0.10399989783763886,
                            0.0023000361397862436,
                            -0.04139997437596321,
                            0.10399990528821945,
                            0.0023000326473265888,
                            -0.04139997810125351,
                            0.10399991273880005,
                            0.002300029154866934,
                            -0.04139998182654381,
                            0.10399991273880005,
                            0.0023000254295766355,
                            -0.041399985551834109,
                            0.10399992018938065,
                            0.0023000219371169807,
                            -0.041399989277124408,
                            0.10399992763996124,
                            0.0023000184446573259,
                            -0.041399989277124408,
                            0.10399992763996124,
                            0.0023000147193670274,
                            -0.0413999930024147,
                            0.10399993509054184,
                            0.0023000112269073726,
                            -0.041399996727705,
                            0.10399994254112244,
                            0.0023000077344477178,
                            -0.0414000004529953,
                            0.10399994254112244,
                            0.002300004009157419,
                            -0.0414000041782856,
                            0.10399994999170304,
                            0.0023000005166977646,
                            -0.0414000041782856,
                            0.10399995744228363,
                            0.0022999970242381098,
                            -0.0414000079035759,
                            0.10399995744228363,
                            0.002299993298947811,
                            -0.041400011628866199,
                            0.10399996489286423,
                            0.0022999898064881565,
                            -0.041400015354156497,
                            0.10399996489286423,
                            0.002299986081197858,
                            -0.04140001907944679,
                            0.10399997234344483,
                            0.002299982588738203,
                            -0.04140001907944679,
                            0.10399997979402542,
                            0.0022999790962785484,
                            -0.04140002280473709,
                            0.10399997979402542,
                            0.0022999753709882499,
                            -0.04140002653002739,
                            0.10399998724460602,
                            0.002299971878528595
                        ]
                    }
                }
            ],
            "script": "Vector3BehaviorTrackScript",
            "accessor": "PositionBlendAccessor"
        },
        {
            "@class": "QuaternionBehaviorTrack",
            "clips": [
                {
                    "@class": "QuaternionBehaviorClip",
                    "beginTime": 0,
                    "duration": 833,
                    "script": "QuaternionValueBehaviorClipScript",
                    "behavior": {
                        "@class": "QuaternionPlainBehavior",
                        "times": [
                            0,
                            166,
                            199,
                            233,
                            266,
                            299,
                            333,
                            366,
                            399,
                            433,
                            466,
                            499,
                            533,
                            566,
                            599,
                            633,
                            666,
                            699,
                            733,
                            766,
                            799,
                            833
                        ],
                        "values": [
                            0.28913578391075137,
                            -0.0035191632341593506,
                            -0.027390174567699434,
                            0.9568896889686585,
                            0.28913578391075137,
                            -0.003519197227433324,
                            -0.02739012986421585,
                            0.9568896889686585,
                            0.29595306515693667,
                            -0.003750051138922572,
                            -0.02688802219927311,
                            0.9548166394233704,
                            0.31657540798187258,
                            -0.004435611888766289,
                            -0.02533944882452488,
                            0.9482184648513794,
                            0.3483961522579193,
                            -0.005456012208014727,
                            -0.022860944271087648,
                            0.9370526671409607,
                            0.3882688283920288,
                            -0.006670231465250254,
                            -0.019594764336943628,
                            0.9213137030601502,
                            0.43304237723350527,
                            -0.007949243299663067,
                            -0.01569950580596924,
                            0.9012017846107483,
                            0.4798247516155243,
                            -0.009137164801359177,
                            -0.011275281198322773,
                            0.8772443532943726,
                            0.5252717137336731,
                            -0.010299687273800373,
                            -0.006819678470492363,
                            0.8508449196815491,
                            0.5673093199729919,
                            -0.011243175715208054,
                            -0.002334055956453085,
                            0.823424756526947,
                            0.6002041697502136,
                            -0.01190025731921196,
                            0.0014448247384279967,
                            0.7997570037841797,
                            0.6321044564247131,
                            -0.012537685222923756,
                            0.0052212742157280449,
                            0.7747642397880554,
                            0.6458727121353149,
                            -0.012783100828528405,
                            0.006949715781956911,
                            0.7633064985275269,
                            0.6594316363334656,
                            -0.013024377636611462,
                            0.008675893768668175,
                            0.7516016364097595,
                            0.6545243859291077,
                            -0.01293949130922556,
                            0.008042828179895878,
                            0.7558873891830444,
                            0.6330475807189941,
                            -0.012554770335555077,
                            0.0053383526392281059,
                            0.7739927172660828,
                            0.5953832864761353,
                            -0.011827797628939152,
                            0.0008377768681384623,
                            0.8033543229103088,
                            0.5444444417953491,
                            -0.010739983059465886,
                            -0.004811099264770746,
                            0.8387143611907959,
                            0.48367321491241457,
                            -0.009287431836128235,
                            -0.010978292673826218,
                            0.8751305341720581,
                            0.4173509180545807,
                            -0.007512168493121862,
                            -0.017094675451517106,
                            0.9085536003112793,
                            0.35059604048728945,
                            -0.005525575019419193,
                            -0.022686438634991647,
                            0.9362356662750244,
                            0.28913578391075137,
                            -0.0035192114301025869,
                            -0.027390150353312494,
                            0.9568896889686585
                        ]
                    }
                }
            ],
            "script": "QuaternionBehaviorTrackScript",
            "accessor": "RotationQBlendAccessor"
        },
        {
            "@class": "Vector3BehaviorTrack",
            "clips": [
                {
                    "@class": "Vector3BehaviorClip",
                    "beginTime": 0,
                    "duration": 833,
                    "script": "Vector3ValueBehaviorClipScript",
                    "behavior": {
                        "@class": "Vector3PlainBehavior",
                        "times": [
                            0,
                            166,
                            199,
                            233,
                            266,
                            299,
                            333,
                            366,
                            399,
                            433,
                            466,
                            499,
                            533,
                            566,
                            599,
                            633,
                            666,
                            699,
                            733,
                            766,
                            799,
                            833
                        ],
                        "values": [
                            0.9999999403953552,
                            0.9999998807907105,
                            0.9999998807907105,
                            0.9999999403953552,
                            0.9999998807907105,
                            0.9999998807907105,
                            0.9999998807907105,
                            0.9999998807907105,
                            0.9999998807907105,
                            0.9999999403953552,
                            0.9999998807907105,
                            0.9999998807907105,
                            0.9999999403953552,
                            0.9999998807907105,
                            0.9999998807907105,
                            0.9999999403953552,
                            0.9999998807907105,
                            0.9999998807907105,
                            0.9999998807907105,
                            0.9999999403953552,
                            0.9999998807907105,
                            0.9999999403953552,
                            0.9999998807907105,
                            0.9999998211860657,
                            0.9999999403953552,
                            0.9999998807907105,
                            0.9999998211860657,
                            0.9999998807907105,
                            1.0,
                            0.9999997615814209,
                            0.9999998807907105,
                            1.0,
                            0.9999998211860657,
                            0.9999998807907105,
                            0.9999999403953552,
                            0.9999998211860657,
                            0.9999998807907105,
                            0.9999999403953552,
                            0.9999998211860657,
                            0.9999998211860657,
                            1.0,
                            0.9999998807907105,
                            0.9999998211860657,
                            1.0,
                            0.9999997615814209,
                            0.9999998807907105,
                            1.0,
                            0.9999998211860657,
                            0.9999998211860657,
                            1.0,
                            0.9999997615814209,
                            0.9999998807907105,
                            1.0,
                            0.9999997615814209,
                            0.9999998807907105,
                            1.0,
                            0.9999998211860657,
                            0.9999998807907105,
                            0.9999999403953552,
                            0.9999997615814209,
                            0.9999998807907105,
                            1.0,
                            0.9999998807907105,
                            0.9999998807907105,
                            0.9999999403953552,
                            0.9999998807907105
                        ]
                    }
                }
            ],
            "script": "Vector3BehaviorTrackScript",
            "accessor": "ScaleBlendAccessor"
        }
    ]
}